siphotonics/__init__.py
siphotonics/__version__.py
siphotonics/command_line.py
siphotonics/effective_index.py
siphotonics/group_index.py
siphotonics/permittivity.py
siphotonics/read_data.py
siphotonics/util.py
siphotonics/data/Si_Palik_Refractive_Index.pickle
siphotonics/data/neff_fitted_Si_fitted_SiO2_width_240_5_700_wav_1200_0p1_1700.csv
siphotonics/data/neff_pol.pickle
siphotonics/data/neff_te0_fitted_Si_fitted_SiO2_width_240_10_700_wav_1200_10_1700.csv
siphotonics/data/neff_te0_fitted_Si_fitted_SiO2_width_240_5_700_wav_1200_0p1_1700.csv
siphotonics/data/neff_te1_fitted_Si_fitted_SiO2_width_240_10_700_wav_1200_10_1700.csv
siphotonics/data/neff_te1_fitted_Si_fitted_SiO2_width_240_5_700_wav_1200_0p1_1700.csv
siphotonics/data/neff_te2_fitted_Si_fitted_SiO2_width_240_10_700_wav_1200_10_1700.csv
siphotonics/data/neff_te2_fitted_Si_fitted_SiO2_width_240_5_700_wav_1200_0p1_1700.csv
siphotonics/data/neff_tm0_fitted_Si_fitted_SiO2_width_240_10_700_wav_1200_10_1700.csv
siphotonics/data/neff_tm0_fitted_Si_fitted_SiO2_width_240_5_700_wav_1200_0p1_1700.csv
siphotonics/data/neff_tm1_fitted_Si_fitted_SiO2_width_240_10_700_wav_1200_10_1700.csv
siphotonics/data/neff_tm1_fitted_Si_fitted_SiO2_width_240_5_700_wav_1200_0p1_1700.csv
siphotonics/data/permittivity.pickle
siphotonics-1.3.2.dist-info/LICENSE
siphotonics-1.3.2.dist-info/METADATA
siphotonics-1.3.2.dist-info/WHEEL
siphotonics-1.3.2.dist-info/top_level.txt
siphotonics-1.3.2.dist-info/RECORD
